dd/__init__.py
dd/cli.py
dd/dd_utils.py
dd/test_queue.py
dd/config/config.json
dd/config/.ipynb_checkpoints/config-checkpoint.json
dd/core/__init__.py
dd/core/compare.py
dd/core/diagnose.py
dd/core/embed.py
dd/core/fuse.py
dd/core/init.py
dd/core/lineage.py
dd/core/monitor.py
dd/core/pull.py
dd/core/push.py
dd/core/train.py
dd/core/treat.py
dd/core/visualize.py
dd/fonts/NanumGothicCoding-Bold.ttf
dd/fonts/NanumGothicCoding-Regular.ttf
dd/hub/run_hub_api.sh
dd/hub/.ipynb_checkpoints/run_hub_api-checkpoint.sh
keti_datadrift-0.1.3.3.dist-info/METADATA
keti_datadrift-0.1.3.3.dist-info/WHEEL
keti_datadrift-0.1.3.3.dist-info/entry_points.txt
keti_datadrift-0.1.3.3.dist-info/top_level.txt
keti_datadrift-0.1.3.3.dist-info/RECORD
