Metadata-Version: 2.4
Name: keti-datadrift
Version: 0.1.3.3
License: Apache2.0
Requires-Dist: fastapi
Requires-Dist: uvicorn
Requires-Dist: requests
Requires-Dist: pandas
Requires-Dist: numpy
Requires-Dist: scikit-learn
Requires-Dist: pyyaml
Requires-Dist: fpdf
Requires-Dist: weasyprint
Dynamic: license
Dynamic: requires-dist
